oddeven_yahwin/__init__.py
oddeven_yahwin/checker.py
oddeven_yahwin-0.1.0.dist-info/METADATA
oddeven_yahwin-0.1.0.dist-info/WHEEL
oddeven_yahwin-0.1.0.dist-info/licenses/LICENSE.txt
oddeven_yahwin-0.1.0.dist-info/RECORD
