Metadata-Version: 2.4
Name: oddeven-yahwin
Version: 0.1.0
Summary: Check if a number is odd or even
Author-email: Yahwin <yahwinlukose0@gmail.com>
License: MIT
License-File: LICENSE.txt
Requires-Python: >=3.7
